Workbook

Sheet Assumptions
A1: Illegal Parking at Bus Stops - OTP Impact Model
A2: Blue cells = inputs you can change. Yellow = key assumptions. All results recalculate.
A4: Parameter | B4: Value | C4: Note / source
A5: Observed blocked-layby cases, AM peak 07:00-10:00 (60 = field survey, 11 locations, one day) | B5: 60 | C5: Source: field survey table, one day, 11 locations
A6: Bus arrivals at the 11 locations, AM peak (from AVL 22 Jul 2026) | B6: 1254 | C6: Source: analysis/runtime_analysis.py -> locations.csv
A7: Bus arrivals at the 11 locations, PM peak 17:00-20:00 (AVL) | B7: 1147 | C7: Same source
A8: PM/AM case intensity factor | B8: =B7/B6 -> 0.91467305 | C8: Default = PM/AM bus exposure ratio; override with a number if surveyed
A9: Average delay per obstructed arrival (seconds) | B9: 30 | C9: Operations estimate (user-provided). Scenarios 15/60/90 s on Model sheet
A10: Operating days per year | B10: 261 | C10: Working days (Mon-Fri). Low 250 / High 305 - see Model sheet
A11: Peak trips/day serving the 11 locations (AVL) | B11: 1042 | C11: Trips with a peak stop event at the 11 locations, 22 Jul 2026
A12: Total trips/day, all 38 affected routes (AVL) | B12: 2999 | C12: 22 Jul 2026 AVL
A13: OTP window: early threshold (seconds) | B13: -60 | C13: RTA rule: more than 1 min early = early
A14: OTP window: late threshold (seconds) | B14: 300 | C14: RTA rule: more than 5 min late = late

Sheet BaseData22Jul
A1: Field survey (one day, 07:00-10:00) x AVL exposure (22 Jul 2026)
A3: Location | B3: Cases AM (3h) | C3: Buses AM peak | D3: Buses PM peak | E3: Buses/day | F3: Cases per 100 AM buses | G3: OTP at stop (day)
A4: Naif Intersection | B4: 5 | C4: 195 | D4: 168 | E4: 1086 | F4: =100*B4/C4 -> 2.5641026 | G4: 0.827
A5: Burj Nahar | B5: 5 | C5: 195 | D5: 169 | E5: 1087 | F5: =100*B5/C5 -> 2.5641026 | G5: 0.845
A6: Al Jafliya | B6: 6 | C6: 45 | D6: 33 | E6: 220 | F6: =100*B6/C6 -> 13.333333 | G6: 0.936
A7: Emirates Tower | B7: 3 | C7: 48 | D7: 40 | E7: 265 | F7: =100*B7/C7 -> 6.25 | G7: 0.916
A8: Al Khail Mall | B8: 2 | C8: 211 | D8: 204 | E8: 1127 | F8: =100*B8/C8 -> 0.9478673 | G8: 0.933
A9: Al Hana Center | B9: 5 | C9: 128 | D9: 113 | E9: 716 | F9: =100*B9/C9 -> 3.90625 | G9: 0.919
A10: Burjuman | B10: 7 | C10: 77 | D10: 78 | E10: 438 | F10: =100*B10/C10 -> 9.0909091 | G10: 0.902
A11: Sharaf DG Metro | B11: 8 | C11: 179 | D11: 178 | E11: 1031 | F11: =100*B11/C11 -> 4.4692737 | G11: 0.787
A12: Al Rigga Metro | B12: 5 | C12: 31 | D12: 26 | E12: 176 | F12: =100*B12/C12 -> 16.129032 | G12: 0.835
A13: Salah Al Din Metro | B13: 4 | C13: 43 | D13: 37 | E13: 236 | F13: =100*B13/C13 -> 9.3023256 | G13: 0.915
A14: Business Bay | B14: 10 | C14: 102 | D14: 101 | E14: 455 | F14: =100*B14/C14 -> 9.8039216 | G14: 0.939
A15: TOTAL | B15: =SUM(B4:B14) -> 60 | C15: =SUM(C4:C14) -> 1254 | D15: =SUM(D4:D14) -> 1147 | E15: =SUM(E4:E14) -> 6837 | F15: =100*B15/C15 -> 4.784689
A17: Source: field survey (cases); data/Runtime_2026-07-22.xlsx via analysis/runtime_analysis.py (all other columns).

Sheet Model
A1: Annual extrapolation & OTP impact (11 surveyed locations only)
A4: Cases per day - AM peak | B4: =Assumptions!B5 -> 60
A5: Cases per day - PM peak (AM x PM factor) | B5: =Assumptions!B5*Assumptions!B8 -> 54.880383
A6: Cases per day - both peaks | B6: =B4+B5 -> 114.88038
A7: Annual blocked-layby cases | B7: =B6*Assumptions!B10 -> 29983.78
A8: Share of AM-peak arrivals obstructed | B8: =Assumptions!B5/Assumptions!B6 -> 0.04784689
A9: Annual direct bus delay (hours) | B9: =B7*Assumptions!B9/3600 -> 249.86483
A10: Annual peak trips serving the 11 locations | B10: =Assumptions!B11*Assumptions!B10 -> 271962
A11: Annual trips, all 38 routes (365 d service) | B11: =Assumptions!B12*365 -> 1094635
A13: Delay scenarios
A14: Delay per case (s) | B14: P(trip flips late) | C14: Extra late trips/yr | D14: dOTP affected peak trips (pp) | E14: dOTP all 38 routes (pp)
A15: 15 | B15: 0.0144 | C15: =$B$7*B15 -> 431.76643 | D15: =100*C15/$B$10 -> 0.15875984 | E15: =100*C15/$B$11 -> 0.039443872
A16: 30 | B16: 0.0259 | C16: =$B$7*B16 -> 776.5799 | D16: =100*C16/$B$10 -> 0.28554721 | E16: =100*C16/$B$11 -> 0.070944187
A17: 60 | B17: 0.0633 | C17: =$B$7*B17 -> 1897.9733 | D17: =100*C17/$B$10 -> 0.69788179 | E17: =100*C17/$B$11 -> 0.17338869
A18: 90 | B18: 0.0902 | C18: =$B$7*B18 -> 2704.5369 | D18: =100*C18/$B$10 -> 0.99445399 | E18: =100*C18/$B$11 -> 0.24707203
A20: Flip probabilities measured from 22 Jul 2026 AVL peak deviation distribution at the 11 locations (analysis/output/flip_probabilities.csv). Delay rows are scenarios; the 30 s row is the operations estimate.
A21: dOTP = extra late trips / trip population, in percentage points. Conservative: single hit per trip, peaks only, 11 locations only.

Sheet NetworkTiers
A1: Network-wide three-tier risk model (GTFS-based)
A2: High = 112 profile-matched stops; Medium/Low = next 400 / following 400 by AM-peak throughput. Rate multipliers are assumptions - adjust the blue cells.
A3: GTFS AM-peak arrivals at the 27 surveyed stops | B3: 2084
A4: Calibrated case rate per AM-peak arrival | B4: =Assumptions!B5/B3 -> 0.028790787
A5: Weekday bus trips with a peak-hour stop event | B5: 9771
A7: Tier | B7: Stops | C7: AM-peak arrivals | D7: Rate multiplier | E7: Cases per AM peak | F7: Annual cases | G7: Delay hours @30s | H7: Extra late trips/yr @30s | I7: Extra late trips/yr @60s | J7: dOTP peak (pp) @30s | K7: dOTP peak (pp) @60s
A8: High (profile-matched) | B8: 112 | C8: 12622 | D8: 1 | E8: =C8*$B$4*D8 -> 363.39731 | F8: =E8*(1+Assumptions!B8)*Assumptions!B10 -> 181600.42 | G8: =F8*Assumptions!B9/3600 -> 1513.3368 | H8: =F8*Model!$B$16 -> 4703.4508 | I8: =F8*Model!$B$17 -> 11495.306 | J8: =100*H8/($B$5*Assumptions!B10) -> 0.18443234 | K8: =100*I8/($B$5*Assumptions!B10) -> 0.4507555
A9: Medium (next 400 by throughput) | B9: 400 | C9: 18657 | D9: 0.5 | E9: =C9*$B$4*D9 -> 268.57486 | F9: =E9*(1+Assumptions!B8)*Assumptions!B10 -> 134214.82 | G9: =F9*Assumptions!B9/3600 -> 1118.4569 | H9: =F9*Model!$B$16 -> 3476.1639 | I9: =F9*Model!$B$17 -> 8495.7983 | J9: =100*H9/($B$5*Assumptions!B10) -> 0.13630781 | K9: =100*I9/($B$5*Assumptions!B10) -> 0.33313838
A10: Low (following 400) | B10: 400 | C10: 8273 | D10: 0.25 | E10: =C10*$B$4*D10 -> 59.546545 | F10: =E10*(1+Assumptions!B8)*Assumptions!B10 -> 29757.175 | G10: =F10*Assumptions!B9/3600 -> 247.97646 | H10: =F10*Model!$B$16 -> 770.71083 | I10: =F10*Model!$B$17 -> 1883.6292 | J10: =100*H10/($B$5*Assumptions!B10) -> 0.030221217 | K10: =100*I10/($B$5*Assumptions!B10) -> 0.07386112
A11: TOTAL | B11: =SUM(B8:B10) -> 912 | C11: =SUM(C8:C10) -> 39552 | E11: =SUM(E8:E10) -> 691.51871 | F11: =SUM(F8:F10) -> 345572.42 | G11: =SUM(G8:G10) -> 2879.7701 | H11: =SUM(H8:H10) -> 8950.3256 | I11: =SUM(I8:I10) -> 21874.734 | J11: =SUM(J8:J10) -> 0.35096137 | K11: =SUM(K8:K10) -> 0.857755
A13: Cases = arrivals x calibrated rate x multiplier; annual = x (1+PM factor) x operating days. Flip probabilities referenced from Model sheet (22 Jul 2026 AVL). Source: analysis/network_scoring.py -> tier_summary.csv

Sheet ROI
A1: Enforcement ROI - fixed vs portable cameras (5 years)
A2: Blue = inputs. NPV discounts year-end cash flows; capex at year 0. Source: analysis/roi_model.py
A4: Fine per violation (AED) | B4: 200
A5: Enforceability rate | B5: 0.7
A6: Collection rate | B6: 0.8
A7: Off-peak uplift factor | B7: 0.2
A8: Deterrence decay - fixed (per yr) | B8: 0.25
A9: Deterrence decay - portable (per yr) | B9: 0.15
A10: Discount rate | B10: 0.07
A11: Fixed camera capex per site (AED) | B11: 40000
A12: Fixed camera opex per site/yr (AED) | B12: 5000
A13: Portable unit capex (AED) | B13: 15000
A14: Portable unit opex/yr (AED) | B14: 60000
A16: Option A - fixed cameras by tier
A17: Tier | B17: Stops | C17: Annual peak cases | D17: Capex (M) | E17: Opex/yr (M) | F17: Revenue yr1 (M) | G17: 5-yr NPV cash (M) | H17: High+Med NPV ->
A18: High | B18: 112 | C18: 181600 | D18: =B18*$B$11/1000000 -> 4.48 | E18: =B18*$B$12/1000000 -> 0.56 | F18: =C18*(1+$B$7)*$B$5*$B$6*$B$4/1000000 -> 24.40704 | G18: =(F18*((1-$B$8)^0/(1+$B$10)^1+(1-$B$8)^1/(1+$B$10)^2+(1-$B$8)^2/(1+$B$10)^3+(1-$B$8)^3/(1+$B$10)^4+(1-$B$8)^4/(1+$B$10)^5))-(E18*(1/(1+$B$10)^1+1/(1+$B$10)^2+1/(1+$B$10)^3+1/(1+$B$10)^4+1/(1+$B$10)^5))-D18 -> 56.591051
A19: Medium | B19: 400 | C19: 134200 | D19: =B19*$B$11/1000000 -> 16 | E19: =B19*$B$12/1000000 -> 2 | F19: =C19*(1+$B$7)*$B$5*$B$6*$B$4/1000000 -> 18.03648 | G19: =(F19*((1-$B$8)^0/(1+$B$10)^1+(1-$B$8)^1/(1+$B$10)^2+(1-$B$8)^2/(1+$B$10)^3+(1-$B$8)^3/(1+$B$10)^4+(1-$B$8)^4/(1+$B$10)^5))-(E19*(1/(1+$B$10)^1+1/(1+$B$10)^2+1/(1+$B$10)^3+1/(1+$B$10)^4+1/(1+$B$10)^5))-D19 -> 22.6271
A20: Low | B20: 400 | C20: 29800 | D20: =B20*$B$11/1000000 -> 16 | E20: =B20*$B$12/1000000 -> 2 | F20: =C20*(1+$B$7)*$B$5*$B$6*$B$4/1000000 -> 4.00512 | G20: =(F20*((1-$B$8)^0/(1+$B$10)^1+(1-$B$8)^1/(1+$B$10)^2+(1-$B$8)^2/(1+$B$10)^3+(1-$B$8)^3/(1+$B$10)^4+(1-$B$8)^4/(1+$B$10)^5))-(E20*(1/(1+$B$10)^1+1/(1+$B$10)^2+1/(1+$B$10)^3+1/(1+$B$10)^4+1/(1+$B$10)^5))-D20 -> -13.802039
A21: TOTAL / High+Medium | G21: =SUM(G18:G20) -> 65.416112 | H21: =G18+G19 -> 79.218152
A23: Option B - portable fleet at High-tier stops (monthly rotation)
A24: Units | B24: Events/stop/day | C24: Capex (M) | D24: Opex/yr (M) | E24: Revenue yr1 (M) | F24: 5-yr NPV cash (M)
A25: 20 | B25: =C18*(1+$B$7)/261/B18 -> 7.454844 | C25: =A25*$B$13/1000000 -> 0.3 | D25: =A25*$B$14/1000000 -> 1.2 | E25: =A25*B25*261*$B$5*$B$6*$B$4/1000000 -> 4.3584 | F25: =(E25*((1-$B$9)^0/(1+$B$10)^1+(1-$B$9)^1/(1+$B$10)^2+(1-$B$9)^2/(1+$B$10)^3+(1-$B$9)^3/(1+$B$10)^4+(1-$B$9)^4/(1+$B$10)^5))-(D25*(1/(1+$B$10)^1+1/(1+$B$10)^2+1/(1+$B$10)^3+1/(1+$B$10)^4+1/(1+$B$10)^5))-C25 -> 8.3233771
A26: 30 | B26: =C18*(1+$B$7)/261/B18 -> 7.454844 | C26: =A26*$B$13/1000000 -> 0.45 | D26: =A26*$B$14/1000000 -> 1.8 | E26: =A26*B26*261*$B$5*$B$6*$B$4/1000000 -> 6.5376 | F26: =(E26*((1-$B$9)^0/(1+$B$10)^1+(1-$B$9)^1/(1+$B$10)^2+(1-$B$9)^2/(1+$B$10)^3+(1-$B$9)^3/(1+$B$10)^4+(1-$B$9)^4/(1+$B$10)^5))-(D26*(1/(1+$B$10)^1+1/(1+$B$10)^2+1/(1+$B$10)^3+1/(1+$B$10)^4+1/(1+$B$10)^5))-C26 -> 12.485066
A27: 40 | B27: =C18*(1+$B$7)/261/B18 -> 7.454844 | C27: =A27*$B$13/1000000 -> 0.6 | D27: =A27*$B$14/1000000 -> 2.4 | E27: =A27*B27*261*$B$5*$B$6*$B$4/1000000 -> 8.7168 | F27: =(E27*((1-$B$9)^0/(1+$B$10)^1+(1-$B$9)^1/(1+$B$10)^2+(1-$B$9)^2/(1+$B$10)^3+(1-$B$9)^3/(1+$B$10)^4+(1-$B$9)^4/(1+$B$10)^5))-(D27*(1/(1+$B$10)^1+1/(1+$B$10)^2+1/(1+$B$10)^3+1/(1+$B$10)^4+1/(1+$B$10)^5))-C27 -> 16.646754
A28: 50 | B28: =C18*(1+$B$7)/261/B18 -> 7.454844 | C28: =A28*$B$13/1000000 -> 0.75 | D28: =A28*$B$14/1000000 -> 3 | E28: =A28*B28*261*$B$5*$B$6*$B$4/1000000 -> 10.896 | F28: =(E28*((1-$B$9)^0/(1+$B$10)^1+(1-$B$9)^1/(1+$B$10)^2+(1-$B$9)^2/(1+$B$10)^3+(1-$B$9)^3/(1+$B$10)^4+(1-$B$9)^4/(1+$B$10)^5))-(D28*(1/(1+$B$10)^1+1/(1+$B$10)^2+1/(1+$B$10)^3+1/(1+$B$10)^4+1/(1+$B$10)^5))-C28 -> 20.808443
A30: Deterrence decay makes revenue decline by design - the permanent return is OTP recovery and safety. AED 500 federal fine scales revenue x2.5. Fine-revenue retention by RTA unconfirmed.

Sheet KerbMonetization
A1: Kerb monetization - charging private operators for legal layby use
A2: Permits + ANPR-billed pay-per-use. Rides on the enforcement cameras (no extra field hardware). Blue = inputs.
A4: Permitted vehicles (licensed operators) | B4: 2000
A5: Permit fee (AED/vehicle/yr) | B5: 1200
A6: Paid dwells per day (network-wide) | B6: 1000
A7: Fee per dwell (AED) | B7: 5
A8: Adoption ramp year 1 | B8: 0.4
A9: Adoption ramp year 2 | B9: 0.8
A10: Adoption ramp year 3+ | B10: 1
A11: Platform capex (AED) | B11: 2000000
A12: Administration opex (AED/yr) | B12: 500000
A13: Discount rate | B13: =ROI!B10 -> 0.07
A15: Steady-state revenue (AED/yr) | B15: =B4*B5+B6*B7*365 -> 4225000
A17: Year | B17: Ramp | C17: Revenue (AED) | D17: Opex (AED) | E17: Net (AED) | F17: PV @ discount
A18: 1 | B18: =B8 -> 0.4 | C18: =$B$15*B18 -> 1690000 | D18: =$B$12 -> 500000 | E18: =C18-D18 -> 1190000 | F18: =E18/(1+$B$13)^A18 -> 1112149.5
A19: 2 | B19: =B9 -> 0.8 | C19: =$B$15*B19 -> 3380000 | D19: =$B$12 -> 500000 | E19: =C19-D19 -> 2880000 | F19: =E19/(1+$B$13)^A19 -> 2515503.5
A20: 3 | B20: =B10 -> 1 | C20: =$B$15*B20 -> 4225000 | D20: =$B$12 -> 500000 | E20: =C20-D20 -> 3725000 | F20: =E20/(1+$B$13)^A20 -> 3040709.6
A21: 4 | B21: =B10 -> 1 | C21: =$B$15*B21 -> 4225000 | D21: =$B$12 -> 500000 | E21: =C21-D21 -> 3725000 | F21: =E21/(1+$B$13)^A21 -> 2841784.7
A22: 5 | B22: =B10 -> 1 | C22: =$B$15*B22 -> 4225000 | D22: =$B$12 -> 500000 | E22: =C22-D22 -> 3725000 | F22: =E22/(1+$B$13)^A22 -> 2655873.5
A23: 5-yr NPV (AED) | F23: =SUM(F18:F22)-B11 -> 10166021
A25: Benchmarks: US airport kerb-access fees (USD 2.50-5/pick-up via geofence), smart loading zones (Pittsburgh, LA, Columbus - camera-billed per minute), Westminster paid coach bays. Source: analysis/roi_model.py
